tf_ai_agents/__init__.py
tf_ai_agents/core.py
tf_ai_agents-0.1.0a1.dist-info/licenses/LICENSE
tf_ai_agents-0.1.0a1.dist-info/METADATA
tf_ai_agents-0.1.0a1.dist-info/WHEEL
tf_ai_agents-0.1.0a1.dist-info/top_level.txt
tf_ai_agents-0.1.0a1.dist-info/RECORD
