Metadata-Version: 2.4
Name: tf-ai-agents
Version: 0.1.0a1
Summary: A Python package for AI agent functionality
Home-page: https://github.com/sonukumar-tf/tf-ai-agents
Author: Sonu Kumar TF
Author-email: Sonu Kumar TF <sonu.kumar@thoughtfocus.com>
License: MIT
Project-URL: Homepage, https://github.com/sonukumar-tf/tf-ai-agents
Project-URL: Repository, https://github.com/sonukumar-tf/tf-ai-agents
Project-URL: Issues, https://github.com/sonukumar-tf/tf-ai-agents/issues
Project-URL: Documentation, https://github.com/sonukumar-tf/tf-ai-agents#readme
Keywords: ai,agents,thoughtfocus,machine learning
Classifier: Development Status :: 3 - Alpha
Classifier: Intended Audience :: Developers
Classifier: License :: OSI Approved :: MIT License
Classifier: Operating System :: OS Independent
Classifier: Programming Language :: Python :: 3
Classifier: Programming Language :: Python :: 3.11
Classifier: Programming Language :: Python :: 3.12
Classifier: Topic :: Software Development :: Libraries :: Python Modules
Classifier: Topic :: Scientific/Engineering :: Artificial Intelligence
Requires-Python: >=3.11
License-File: LICENSE
Provides-Extra: dev
Requires-Dist: pytest>=6.0; extra == "dev"
Requires-Dist: pytest-cov>=2.0; extra == "dev"
Requires-Dist: black>=21.0; extra == "dev"
Requires-Dist: flake8>=3.8; extra == "dev"
Requires-Dist: mypy>=0.800; extra == "dev"
Requires-Dist: isort>=5.0; extra == "dev"
Provides-Extra: docs
Requires-Dist: sphinx>=4.0; extra == "docs"
Requires-Dist: sphinx-rtd-theme>=1.0; extra == "docs"
Dynamic: author
Dynamic: home-page
Dynamic: license-file
Dynamic: requires-python
